pymailbox.py
pymailer.py
pymailbox-0.0.1.dist-info/METADATA
pymailbox-0.0.1.dist-info/WHEEL
pymailbox-0.0.1.dist-info/top_level.txt
pymailbox-0.0.1.dist-info/RECORD
