Metadata-Version: 2.4
Name: pymailbox
Version: 0.0.1
Summary: This is python email package
Classifier: Programming Language :: Python :: 3
Classifier: License :: OSI Approved :: MIT License
Classifier: Operating System :: OS Independent
Provides-Extra: dev
Requires-Dist: pytest>=3.7; extra == "dev"
Dynamic: classifier
Dynamic: provides-extra
Dynamic: summary
